quantjourney/sdk/ADMIN.md
quantjourney/sdk/README.md
quantjourney/sdk/__init__.py
quantjourney/sdk/auth.py
quantjourney/sdk/client.py
quantjourney/sdk/connectors/analytics.py
quantjourney/sdk/connectors/bt.py
quantjourney/sdk/connectors/cboe.py
quantjourney/sdk/connectors/ccxt.py
quantjourney/sdk/connectors/cftc.py
quantjourney/sdk/connectors/cnnf.py
quantjourney/sdk/connectors/eod.py
quantjourney/sdk/connectors/ff.py
quantjourney/sdk/connectors/fmp.py
quantjourney/sdk/connectors/fred.py
quantjourney/sdk/connectors/imf.py
quantjourney/sdk/connectors/insider.py
quantjourney/sdk/connectors/multpl.py
quantjourney/sdk/connectors/oecd.py
quantjourney/sdk/connectors/openfigi.py
quantjourney/sdk/connectors/sec.py
quantjourney/sdk/connectors/universe.py
quantjourney/sdk/connectors/yf.py
quantjourney/sdk/payloads.py
quantjourney/sdk/registry.py
quantjourney/sdk/routers.yaml
quantjourney-5.1.0.dist-info/METADATA
quantjourney-5.1.0.dist-info/WHEEL
quantjourney-5.1.0.dist-info/licenses/LICENSE
quantjourney-5.1.0.dist-info/RECORD
