Metadata-Version: 2.4
Name: quantjourney
Version: 5.1.0
Summary: QuantJourney SDK
License: Proprietary
License-File: LICENSE
Keywords: quant,finance,data,sdk,api
Author: QuantJourney
Author-email: support@quantjourney.pro
Requires-Python: >=3.12,<3.15
Classifier: Development Status :: 4 - Beta
Classifier: Intended Audience :: Developers
Classifier: License :: Other/Proprietary License
Classifier: Programming Language :: Python :: 3
Classifier: Programming Language :: Python :: 3.12
Classifier: Programming Language :: Python :: 3.13
Classifier: Programming Language :: Python :: 3.14
Classifier: Topic :: Office/Business :: Financial :: Investment
Requires-Dist: PyYAML (>=6,<7)
Requires-Dist: requests (>=2.31,<3)
Project-URL: Homepage, https://github.com/QuantJourneyOrg/_repo_quantjourney_sdk
Project-URL: Repository, https://github.com/QuantJourneyOrg/_repo_quantjourney_sdk
